telegram_gifts_fetcher/__init__.py
telegram_gifts_fetcher/client.py
telegram_gifts_fetcher/config.py
telegram_gifts_fetcher/models.py
telegram_gifts_fetcher/tl_objects.py
telegram_gifts_fetcher-2.1.4.1.dist-info/licenses/LICENSE
telegram_gifts_fetcher-2.1.4.1.dist-info/METADATA
telegram_gifts_fetcher-2.1.4.1.dist-info/WHEEL
telegram_gifts_fetcher-2.1.4.1.dist-info/top_level.txt
telegram_gifts_fetcher-2.1.4.1.dist-info/RECORD
