Metadata-Version: 2.4
Name: telegram-gifts-fetcher
Version: 2.1.4.1
Summary: A Python library to fetch Telegram gifts data
Author: Th3ryks
Project-URL: Homepage, https://github.com/Th3ryks/TelegramGiftsFetcher
Project-URL: Bug Reports, https://github.com/Th3ryks/TelegramGiftsFetcher/issues
Project-URL: Source, https://github.com/Th3ryks/TelegramGiftsFetcher
Classifier: Development Status :: 4 - Beta
Classifier: Intended Audience :: Developers
Classifier: License :: OSI Approved :: MIT License
Classifier: Operating System :: OS Independent
Classifier: Programming Language :: Python :: 3
Classifier: Programming Language :: Python :: 3.8
Classifier: Programming Language :: Python :: 3.9
Classifier: Programming Language :: Python :: 3.10
Classifier: Programming Language :: Python :: 3.11
Classifier: Programming Language :: Python :: 3.12
Requires-Python: >=3.8
License-File: LICENSE
Requires-Dist: telethon==1.40.0
Requires-Dist: python-dotenv==1.0.0
Requires-Dist: colorama==0.4.6
Provides-Extra: dev
Requires-Dist: pytest>=6.0; extra == "dev"
Requires-Dist: pytest-asyncio; extra == "dev"
Requires-Dist: black; extra == "dev"
Requires-Dist: ruff; extra == "dev"
Dynamic: license-file
